pcx/__init__.py
pcx/core/__init__.py
pcx/core/_module.py
pcx/core/_parameter.py
pcx/core/_random.py
pcx/core/_static.py
pcx/core/_tree.py
pcx/functional/__init__.py
pcx/functional/_flow.py
pcx/functional/_transform.py
pcx/nn/__init__.py
pcx/nn/_layer.py
pcx/nn/_parameter.py
pcx/nn/_shared.py
pcx/nn/_stateful.py
pcx/predictive_coding/__init__.py
pcx/predictive_coding/_energy.py
pcx/predictive_coding/_energy_module.py
pcx/predictive_coding/_parameter.py
pcx/predictive_coding/_vode.py
pcx/utils/__init__.py
pcx/utils/_data.py
pcx/utils/_mask.py
pcx/utils/_misc.py
pcx/utils/_optim.py
pcx/utils/_serialisation.py
pcx-0.6.3.dist-info/LICENSE
pcx-0.6.3.dist-info/METADATA
pcx-0.6.3.dist-info/WHEEL
pcx-0.6.3.dist-info/RECORD
