Metadata-Version: 2.1
Name: pcx
Version: 0.6.3
Summary: PCX is a Python JAX-based library designed to develop highly configurable predictive coding networks.
Home-page: https://github.com/liukidar/pcx
License: Apache-2.0
Keywords: predictive coding,machine learning,neuroscience
Author: Luca Pinchetti
Author-email: luca.pinchetti@cs.ox.ac.uk
Requires-Python: >=3.11,<4.0
Classifier: License :: OSI Approved :: Apache Software License
Classifier: Programming Language :: Python :: 3
Classifier: Programming Language :: Python :: 3.11
Classifier: Programming Language :: Python :: 3.12
Classifier: Programming Language :: Python :: 3.13
Classifier: Programming Language :: Python :: 3 :: Only
Classifier: Programming Language :: Python :: 3.10
Requires-Dist: equinox (>=0.11.7,<0.12.0)
Requires-Dist: jax (>=0.4.33,<0.5.0)
Requires-Dist: optax (>=0.2.3,<0.3.0)
Project-URL: Documentation, https://pcx.readthedocs.io/en/latest/
Project-URL: Repository, https://github.com/liukidar/pcx
